LICENSE
MANIFEST.in
README.md
setup.py
photos_where/__init__.py
photos_where/cities.csv
photos_where/main.py
photos_where/where.py
photos_where/world.svg
photos_where.egg-info/PKG-INFO
photos_where.egg-info/SOURCES.txt
photos_where.egg-info/dependency_links.txt
photos_where.egg-info/entry_points.txt
photos_where.egg-info/requires.txt
photos_where.egg-info/top_level.txt