Metadata-Version: 2.1
Name: photos-where
Version: 2.2
Summary: Analyze exif data
Home-page: https://github.com/visgean/where
Author: Visgean
Author-email: visgean@gmail.com
License: MIT
Keywords: exif sql
Classifier: License :: OSI Approved :: MIT License
Classifier: Programming Language :: Python :: 3
Classifier: Programming Language :: Python :: 3.7
License-File: LICENSE
Requires-Dist: exif2pandas
Requires-Dist: pandas
Requires-Dist: matplotlib
Requires-Dist: reverse-geocoder==1.5.1
Requires-Dist: pyarrow
Requires-Dist: Jinja2
Requires-Dist: seaborn
